covidcasev.py
covidcasev-0.0.6.dist-info/METADATA
covidcasev-0.0.6.dist-info/WHEEL
covidcasev-0.0.6.dist-info/entry_points.txt
covidcasev-0.0.6.dist-info/top_level.txt
covidcasev-0.0.6.dist-info/RECORD
