Metadata-Version: 2.1
Name: covidcasev
Version: 0.0.6
Summary: A package for visualizing covid-19's vaccinations and infected people of each countries
Home-page: https://github.com/yugo-Ishihara/covidcasev
Author: Yugo Ishihara
Author-email: s2022041@stu.musashino-u.ac.jp
License: UNKNOWN
Project-URL: covidcasev, https://github.com/yugo-Ishihara/covidcasev
Platform: UNKNOWN
Classifier: Programming Language :: Python :: 3
Classifier: License :: OSI Approved :: MIT License
Classifier: Operating System :: OS Independent
Requires-Python: >=3.7
